freqCut/__init__.py
freqCut/cutter.py
freqCut-1.2.dist-info/METADATA
freqCut-1.2.dist-info/WHEEL
freqCut-1.2.dist-info/top_level.txt
freqCut-1.2.dist-info/RECORD
