Metadata-Version: 2.1
Name: freqCut
Version: 1.2
Summary: 全局最优的等频分组包，通过最小化每组占比与指定占比的残差最小平方和来实现
Home-page: https://github.com/wangwenhao-DATA-OG/freqCut
Author: 王文皓(wangwenhao)
Author-email: DATA-OG@139.com
License: UNKNOWN
Platform: UNKNOWN
Classifier: Programming Language :: Python :: 3
Classifier: License :: OSI Approved :: Apache Software License
Classifier: Operating System :: OS Independent
Requires-Python: >=3.0
Requires-Dist: DagLpDp (>=0.1.1)
